datatext/__init__.py
datatext/core.py
datatext/exceptions.py
datatext/query.py
datatext-1.0.0.dist-info/METADATA
datatext-1.0.0.dist-info/WHEEL
datatext-1.0.0.dist-info/top_level.txt
datatext-1.0.0.dist-info/RECORD
